score_ecard/__init__.py
score_ecard/ecard_model.py
score_ecard/ecard_model_lite.py
score_ecard/ecard_model_v2.py
score_ecard/score_card.py
score_ecard/features/__init__.py
score_ecard/features/factor_screening.py
score_ecard/features/layered_woe.py
score_ecard/features/randomforest_blocks.py
score_ecard/features/xgboost_blocks.py
score_ecard/features/xgboost_woe.py
score_ecard/util/__init__.py
score_ecard/util/ecard_explanation.py
score_ecard/util/ecard_standardized.py
score_ecard/util/interacting_multiple_model.py
score_ecard/util/risk_strategy_report.py
score_ecard/util/util.py
score_ecard-1.2.23.dist-info/DESCRIPTION.rst
score_ecard-1.2.23.dist-info/METADATA
score_ecard-1.2.23.dist-info/RECORD
score_ecard-1.2.23.dist-info/WHEEL
score_ecard-1.2.23.dist-info/metadata.json
score_ecard-1.2.23.dist-info/top_level.txt
